[{"name":"New Zealand","matches":[{"opponenetTeam":"England","teamScore":"241/8","opponentScore":"241","result":"Match tied"},{"opponenetTeam":"India","teamScore":"239/8","opponentScore":"221","result":"New Zealand won by 18 runs"},{"opponenetTeam":"England","teamScore":"186","opponentScore":"305/8","result":"England won by 119 runs"},{"opponenetTeam":"Australia","teamScore":"157","opponentScore":"243/9","result":"Australia won by 86 runs"},{"opponenetTeam":"Pakistan","teamScore":"237/6","opponentScore":"241/4","result":"Pakistan won by 6 wickets (with 5 balls remaining)"},{"opponenetTeam":"West Indies","teamScore":"291/8","opponentScore":"286","result":"New Zealand won by 5 runs"},{"opponenetTeam":"South Africa","teamScore":"245/6","opponentScore":"241/6","result":"New Zealand won by 4 wickets (with 3 balls remaining)"},{"opponenetTeam":"India","opponentScore":"","result":"Match abandoned without a ball bowled"},{"opponenetTeam":"Afghanistan","teamScore":"173/3","opponentScore":"172","result":"New Zealand won by 7 wickets (with 107 balls remaining)"},{"opponenetTeam":"Bangladesh","teamScore":"248/8","opponentScore":"244","result":"New Zealand won by 2 wickets (with 17 balls remaining)"},{"opponenetTeam":"Sri Lanka","teamScore":"137/0","opponentScore":"136","result":"New Zealand won by 10 wickets (with 203 balls remaining)"}]},{"name":"England","matches":[{"opponenetTeam":"New Zealand","teamScore":"241","opponentScore":"241/8","result":"Match tied"},{"opponenetTeam":"Australia","teamScore":"226/2","opponentScore":"223","result":"England won by 8 wickets (with 107 balls remaining)"},{"opponenetTeam":"New Zealand","teamScore":"305/8","opponentScore":"186","result":"England won by 119 runs"},{"opponenetTeam":"India","teamScore":"337/7","opponentScore":"306/5","result":"England won by 31 runs"},{"opponenetTeam":"Australia","teamScore":"221","opponentScore":"285/7","result":"Australia won by 64 runs"},{"opponenetTeam":"Sri Lanka","teamScore":"212","opponentScore":"232/9","result":"Sri Lanka won by 20 runs"},{"opponenetTeam":"Afghanistan","teamScore":"397/6","opponentScore":"247/8","result":"England won by 150 runs"},{"opponenetTeam":"West Indies","teamScore":"213/2","opponentScore":"212","result":"England won by 8 wickets (with 101 balls remaining)"},{"opponenetTeam":"Bangladesh","teamScore":"386/6","opponentScore":"280","result":"England won by 106 runs"},{"opponenetTeam":"Pakistan","teamScore":"334/9","opponentScore":"348/8","result":"Pakistan won by 14 runs"},{"opponenetTeam":"South Africa","teamScore":"311/8","opponentScore":"207","result":"England won by 104 runs"}]},{"name":"Australia","matches":[{"opponenetTeam":"England","teamScore":"223","opponentScore":"226/2","result":"England won by 8 wickets (with 107 balls remaining)"},{"opponenetTeam":"South Africa","teamScore":"315","opponentScore":"325/6","result":"South Africa won by 10 runs"},{"opponenetTeam":"New Zealand","teamScore":"243/9","opponentScore":"157","result":"Australia won by 86 runs"},{"opponenetTeam":"England","teamScore":"285/7","opponentScore":"221","result":"Australia won by 64 runs"},{"opponenetTeam":"Bangladesh","teamScore":"381/5","opponentScore":"333/8","result":"Australia won by 48 runs"},{"opponenetTeam":"Sri Lanka","teamScore":"334/7","opponentScore":"247","result":"Australia won by 87 runs"},{"opponenetTeam":"Pakistan","teamScore":"307","opponentScore":"266","result":"Australia won by 41 runs"},{"opponenetTeam":"India","teamScore":"316","opponentScore":"352/5","result":"India won by 36 runs"},{"opponenetTeam":"West Indies","teamScore":"288","opponentScore":"273/9","result":"Australia won by 15 runs"},{"opponenetTeam":"Afghanistan","teamScore":"209/3","opponentScore":"207","result":"Australia won by 7 wickets (with 91 balls remaining)"}]},{"name":"India","matches":[{"opponenetTeam":"New Zealand","teamScore":"221","opponentScore":"239/8","result":"New Zealand won by 18 runs"},{"opponenetTeam":"Sri Lanka","teamScore":"265/3","opponentScore":"264/7","result":"India won by 7 wickets (with 39 balls remaining)"},{"opponenetTeam":"Bangladesh","teamScore":"314/9","opponentScore":"286","result":"India won by 28 runs"},{"opponenetTeam":"England","teamScore":"306/5","opponentScore":"337/7","result":"England won by 31 runs"},{"opponenetTeam":"West Indies","teamScore":"268/7","opponentScore":"143","result":"India won by 125 runs"},{"opponenetTeam":"Afghanistan","teamScore":"224/8","opponentScore":"213","result":"India won by 11 runs"},{"opponenetTeam":"Pakistan","teamScore":"336/5","opponentScore":"212/6","result":"India won by 89 runs (D/L method)"},{"opponenetTeam":"New Zealand","teamScore":"","result":"Match abandoned without a ball bowled"},{"opponenetTeam":"Australia","teamScore":"352/5","opponentScore":"316","result":"India won by 36 runs"},{"opponenetTeam":"South Africa","teamScore":"230/4","opponentScore":"227/9","result":"India won by 6 wickets (with 15 balls remaining)"}]},{"name":"South Africa","matches":[{"opponenetTeam":"Australia","teamScore":"325/6","opponentScore":"315","result":"South Africa won by 10 runs"},{"opponenetTeam":"Sri Lanka","teamScore":"206/1","opponentScore":"203","result":"South Africa won by 9 wickets (with 76 balls remaining)"},{"opponenetTeam":"Pakistan","teamScore":"259/9","opponentScore":"308/7","result":"Pakistan won by 49 runs"},{"opponenetTeam":"New Zealand","teamScore":"241/6","opponentScore":"245/6","result":"New Zealand won by 4 wickets (with 3 balls remaining)"},{"opponenetTeam":"Afghanistan","teamScore":"131/1","opponentScore":"125","result":"South Africa won by 9 wickets (with 116 balls remaining) (D/L method)"},{"opponenetTeam":"West Indies","teamScore":"29/2","opponentScore":"","result":"No result"},{"opponenetTeam":"India","teamScore":"227/9","opponentScore":"230/4","result":"India won by 6 wickets (with 15 balls remaining)"},{"opponenetTeam":"Bangladesh","teamScore":"309/8","opponentScore":"330/6","result":"Bangladesh won by 21 runs"},{"opponenetTeam":"England","teamScore":"207","opponentScore":"311/8","result":"England won by 104 runs"}]},{"name":"Sri Lanka","matches":[{"opponenetTeam":"India","teamScore":"264/7","opponentScore":"265/3","result":"India won by 7 wickets (with 39 balls remaining)"},{"opponenetTeam":"West Indies","teamScore":"338/6","opponentScore":"315/9","result":"Sri Lanka won by 23 runs"},{"opponenetTeam":"South Africa","teamScore":"203","opponentScore":"206/1","result":"South Africa won by 9 wickets (with 76 balls remaining)"},{"opponenetTeam":"England","teamScore":"232/9","opponentScore":"212","result":"Sri Lanka won by 20 runs"},{"opponenetTeam":"Australia","teamScore":"247","opponentScore":"334/7","result":"Australia won by 87 runs"},{"opponenetTeam":"Bangladesh","opponentScore":"","result":"Match abandoned without a ball bowled"},{"opponenetTeam":"Pakistan","opponentScore":"","result":"Match abandoned without a ball bowled"},{"opponenetTeam":"Afghanistan","teamScore":"201","opponentScore":"152","result":"Sri Lanka won by 34 runs (D/L method)"},{"opponenetTeam":"New Zealand","teamScore":"136","opponentScore":"137/0","result":"New Zealand won by 10 wickets (with 203 balls remaining)"}]},{"name":"Pakistan","matches":[{"opponenetTeam":"Bangladesh","teamScore":"315/9","opponentScore":"221","result":"Pakistan won by 94 runs"},{"opponenetTeam":"Afghanistan","teamScore":"230/7","opponentScore":"227/9","result":"Pakistan won by 3 wickets (with 2 balls remaining)"},{"opponenetTeam":"New Zealand","teamScore":"241/4","opponentScore":"237/6","result":"Pakistan won by 6 wickets (with 5 balls remaining)"},{"opponenetTeam":"South Africa","teamScore":"308/7","opponentScore":"259/9","result":"Pakistan won by 49 runs"},{"opponenetTeam":"India","teamScore":"212/6","opponentScore":"336/5","result":"India won by 89 runs (D/L method)"},{"opponenetTeam":"Australia","teamScore":"266","opponentScore":"307","result":"Australia won by 41 runs"},{"opponenetTeam":"Sri Lanka","teamScore":"","result":"Match abandoned without a ball bowled"},{"opponenetTeam":"England","teamScore":"348/8","opponentScore":"334/9","result":"Pakistan won by 14 runs"},{"opponenetTeam":"West Indies","teamScore":"105","opponentScore":"108/3","result":"West Indies won by 7 wickets (with 218 balls remaining)"}]},{"name":"Bangladesh","matches":[{"opponenetTeam":"Pakistan","teamScore":"221","opponentScore":"315/9","result":"Pakistan won by 94 runs"},{"opponenetTeam":"India","teamScore":"286","opponentScore":"314/9","result":"India won by 28 runs"},{"opponenetTeam":"Afghanistan","teamScore":"262/7","opponentScore":"200","result":"Bangladesh won by 62 runs"},{"opponenetTeam":"Australia","teamScore":"333/8","opponentScore":"381/5","result":"Australia won by 48 runs"},{"opponenetTeam":"West Indies","teamScore":"322/3","opponentScore":"321/8","result":"Bangladesh won by 7 wickets (with 51 balls remaining)"},{"opponenetTeam":"Sri Lanka","teamScore":"","result":"Match abandoned without a ball bowled"},{"opponenetTeam":"England","teamScore":"280","opponentScore":"386/6","result":"England won by 106 runs"},{"opponenetTeam":"New Zealand","teamScore":"244","opponentScore":"248/8","result":"New Zealand won by 2 wickets (with 17 balls remaining)"},{"opponenetTeam":"South Africa","teamScore":"330/6","opponentScore":"309/8","result":"Bangladesh won by 21 runs"}]},{"name":"West Indies","matches":[{"opponenetTeam":"Afghanistan","teamScore":"311/6","opponentScore":"288","result":"West Indies won by 23 runs"},{"opponenetTeam":"Sri Lanka","teamScore":"315/9","opponentScore":"338/6","result":"Sri Lanka won by 23 runs"},{"opponenetTeam":"India","teamScore":"143","opponentScore":"268/7","result":"India won by 125 runs"},{"opponenetTeam":"New Zealand","teamScore":"286","opponentScore":"291/8","result":"New Zealand won by 5 runs"},{"opponenetTeam":"Bangladesh","teamScore":"321/8","opponentScore":"322/3","result":"Bangladesh won by 7 wickets (with 51 balls remaining)"},{"opponenetTeam":"England","teamScore":"212","opponentScore":"213/2","result":"England won by 8 wickets (with 101 balls remaining)"},{"opponenetTeam":"South Africa","teamScore":"","opponentScore":"29/2","result":"No result"},{"opponenetTeam":"Australia","teamScore":"273/9","opponentScore":"288","result":"Australia won by 15 runs"},{"opponenetTeam":"Pakistan","teamScore":"108/3","opponentScore":"105","result":"West Indies won by 7 wickets (with 218 balls remaining)"}]},{"name":"Afghanistan","matches":[{"opponenetTeam":"West Indies","teamScore":"288","opponentScore":"311/6","result":"West Indies won by 23 runs"},{"opponenetTeam":"Pakistan","teamScore":"227/9","opponentScore":"230/7","result":"Pakistan won by 3 wickets (with 2 balls remaining)"},{"opponenetTeam":"Bangladesh","teamScore":"200","opponentScore":"262/7","result":"Bangladesh won by 62 runs"},{"opponenetTeam":"India","teamScore":"213","opponentScore":"224/8","result":"India won by 11 runs"},{"opponenetTeam":"England","teamScore":"247/8","opponentScore":"397/6","result":"England won by 150 runs"},{"opponenetTeam":"South Africa","teamScore":"125","opponentScore":"131/1","result":"South Africa won by 9 wickets (with 116 balls remaining) (D/L method)"},{"opponenetTeam":"New Zealand","teamScore":"172","opponentScore":"173/3","result":"New Zealand won by 7 wickets (with 107 balls remaining)"},{"opponenetTeam":"Sri Lanka","teamScore":"152","opponentScore":"201","result":"Sri Lanka won by 34 runs (D/L method)"},{"opponenetTeam":"Australia","teamScore":"207","opponentScore":"209/3","result":"Australia won by 7 wickets (with 91 balls remaining)"}]}]